dumbo_esse3/__init__.py
dumbo_esse3/__main__.py
dumbo_esse3/cli.py
dumbo_esse3/esse3_wrapper.py
dumbo_esse3/primitives.py
dumbo_esse3-0.4.9.dist-info/LICENSE
dumbo_esse3-0.4.9.dist-info/METADATA
dumbo_esse3-0.4.9.dist-info/WHEEL
dumbo_esse3-0.4.9.dist-info/RECORD
