Metadata-Version: 2.1
Name: dumbo-esse3
Version: 0.4.9
Summary: Esse3 command line utility, to save my future time!
Author: Mario Alviano
Author-email: mario.alviano@gmail.com
Requires-Python: >=3.11,<4.0
Classifier: Programming Language :: Python :: 3
Classifier: Programming Language :: Python :: 3.11
Classifier: Programming Language :: Python :: 3.12
Requires-Dist: dateutils (>=0.6.12,<0.7.0)
Requires-Dist: dumbo-utils (>=0.1.4,<0.2.0)
Requires-Dist: lxml (>=4.9.2,<5.0.0)
Requires-Dist: selenium (>=4.4.3,<5.0.0)
